xyutils/__init__.py
xyutils/disp.py
xyutils/log.py
xyutils/os.py
xyutils/seed.py
xyutils/time.py
xyutils/video.py
xyutils-0.0.1.dist-info/METADATA
xyutils-0.0.1.dist-info/WHEEL
xyutils-0.0.1.dist-info/top_level.txt
xyutils-0.0.1.dist-info/RECORD
