Metadata-Version: 2.1
Name: xyutils
Version: 0.0.1
Summary: some commonly used tools.
Author: lixianyang
Requires-Dist: colorlog
